filewitch/__init__.py
filewitch/cli.py
filewitch/convert.py
filewitch-0.2.1.dist-info/licenses/License
filewitch-0.2.1.dist-info/METADATA
filewitch-0.2.1.dist-info/WHEEL
filewitch-0.2.1.dist-info/entry_points.txt
filewitch-0.2.1.dist-info/top_level.txt
filewitch-0.2.1.dist-info/RECORD
