Metadata-Version: 2.4
Name: filewitch
Version: 0.2.1
Summary: A Python library for converting files between different formats
Home-page: https://github.com/Rktim/filewitch
Author: Raktim Kalita
Author-email: raktimkalita.ai@gmail.com
License: MIT
Classifier: Development Status :: 4 - Beta
Classifier: Intended Audience :: Developers
Classifier: License :: OSI Approved :: MIT License
Classifier: Operating System :: OS Independent
Classifier: Programming Language :: Python :: 3
Classifier: Programming Language :: Python :: 3.7
Classifier: Programming Language :: Python :: 3.8
Classifier: Programming Language :: Python :: 3.9
Classifier: Programming Language :: Python :: 3.10
Classifier: Programming Language :: Python :: 3.11
Requires-Python: >=3.7
License-File: License
Requires-Dist: pandas>=1.5.0
Requires-Dist: openpyxl>=3.1.0
Requires-Dist: python-docx>=0.8.11
Requires-Dist: click>=8.0.0
Requires-Dist: python-pptx>=0.6.21
Requires-Dist: reportlab>=4.0.4
Requires-Dist: Pillow>=10.0.0
Requires-Dist: docx2pdf>=0.1.8
Dynamic: author
Dynamic: author-email
Dynamic: classifier
Dynamic: description
Dynamic: description-content-type
Dynamic: home-page
Dynamic: license
Dynamic: license-file
Dynamic: requires-dist
Dynamic: requires-python
Dynamic: summary
